{"": 78, "init": 458, "axis": 232, "super": 696, "removeClass": 682, "foo:": 539, "arc": 622, "wrap": 494, "tickFormat": 348, "me": 243, "panel": 254, "user": 820, "||": 42, "elem": 709, "on": 110, "radius": 394, ">=": 520, "unit": 415, "localhost": 833, "done": 142, "outerDiv": 878, "quadtree": 451, "min": 246, "mod_ctype": 241, "key": 182, "var": 20, "identity": 845, "333333": 761, "links": 978, "parse": 238, "polygonContains": 603, "y1": 647, "mode": 386, "destroy": 688, "items": 711, "timeDay": 615, "$$": 240, "elems": 923, "node": 70, "23": 226, "coordinates": 333, "observes": 607, "isArray": 642, "keyCode": 862, "{": 12, "builtin": 260, "return": 36, "all": 549, "key:": 623, "42": 314, "seconds": 966, "6": 50, "width": 94, "href": 750, "dir": 685, "debug": 512, "html": 294, "styles": 975, "equal": 24, "viewport": 851, "value;": 759, "lib": 511, "children": 322, "brush": 741, "drag": 504, "classes": 690, "remove": 206, "new": 56, "ticks": 161, "child": 577, "calendar": 800, "CustomPropTypes": 857, "er": 353, "env": 527, "2012": 175, "sort": 466, "get": 162, ";": 8, "scatter": 854, "css": 432, "2014": 898, "pt": 601, "mock": 374, "header": 551, "extent": 289, "Date": 178, "plain": 799, "16": 337, "d3_quadtree": 882, "moment": 101, "curve": 686, "size": 184, "step": 367, "property": 356, "message": 501, "one": 266, "out": 827, "0x01": 956, "unbox": 470, "off": 722, "wfloat": 891, "\\n": 583, "cache": 299, "px": 635, "3": 32, "change": 590, "nice": 521, "option": 476, "__transition": 772, "yScale": 787, "correct": 982, "context": 156, "m": 123, "re": 634, "L": 947, "raw": 573, "document": 144, "expect": 62, "ordinal": 562, "not": 169, "non": 908, "response": 828, "window": 257, "pie": 755, "getAttribute": 829, "utils": 308, "entry": 728, "dom": 126, "selection": 143, "1000": 537, "refresh": 766, "dispatch": 373, "model": 264, "def": 154, "d": 37, "x": 33, "vars": 280, "34": 924, "of": 166, "src": 598, "server": 581, "true": 58, "padding": 433, "fail": 853, "255": 683, "sandbox": 889, "reset": 872, "%": 717, "timeout": 693, "handle": 804, "colors": 609, "_id": 778, "set:": 482, "0x80": 775, "!arguments": 938, "handler": 791, "style": 85, "dot": 976, "1900": 552, "label": 335, "lonlat": 651, "cb": 627, "tmp": 681, "lineEnd": 926, "span": 297, "div>": 597, "pos": 329, "10": 64, "log": 200, "n": 252, "write": 377, "origin": 901, "^": 719, "options": 31, "callback": 224, "attr": 49, "infinity": 513, "stopPropagation": 909, "target": 186, "require": 29, "50": 279, "hosts": 578, "rangeBand": 890, "only": 586, "order": 892, "!!options": 423, "action": 873, "element": 124, "30": 237, "merge": 625, "with": 229, "sqrt": 689, "<div": 916, "chunk": 895, "font": 700, "mouseover": 989, "null;": 231, "<EOS>": 3, "results": 452, "-": 22, "sync": 672, "picker": 917, "id;": 921, "500": 631, "type:": 334, "prop": 605, "1989": 957, "suite": 779, "limit": 727, "title": 375, "weeks": 492, "y;": 813, "Backbone": 902, "cm": 247, "buf": 484, "8": 86, "height": 104, "body": 114, "catch": 599, "Dec": 698, "constants": 752, "return;": 343, "undefined": 120, "Object": 291, "name": 140, "focus": 626, "function": 19, "parses": 666, "boxes": 856, "physical": 352, "calc": 875, "reader": 801, "filter": 302, "10000": 972, "utcDay": 952, "View": 636, "exactly": 326, "margin": 160, "names": 687, "optional": 950, "numbers": 384, "quantile": 694, "<PAD>": 0, "end": 35, "common": 497, "+": 25, "59": 164, "token": 858, "ceil": 330, "st": 606, "pathEqual": 613, "bytes": 935, "stroke": 390, "innerHTML": 695, "class": 121, "after": 628, "_": 113, "selector": 434, "string": 165, "msg": 831, "data:": 544, "scale": 68, "readPreference": 705, "toHaveBeenCalledWith": 941, "hide": 383, "split": 576, "invert": 448, "run": 566, "300": 814, "31": 215, "skip": 949, "args": 263, "ASSERT": 108, "returnValue": 852, "break;": 351, "print": 633, "bar": 135, "local": 61, "matches": 803, "length": 66, "draw": 431, "description:": 776, "case": 259, "buffer": 88, "show": 336, "80": 560, "top:": 781, "layer": 316, "week": 71, "nv": 618, "red": 429, "b:": 572, "day": 648, "bgcolor": 877, "input": 239, "PropTypes": 223, "right:": 903, "toEqual": 300, "0": 17, "if": 28, "nodes": 276, "logger": 832, "wrapper": 477, "join": 262, "18": 614, "group": 419, "velocity": 899, "str": 860, "output": 638, "labels": 393, "last": 768, "CSSRule": 542, "q": 331, "sourceMap": 943, "button": 754, "does": 378, "types": 570, "classed": 235, "documentElement": 807, "version": 676, "interaction": 823, "elements": 385, "format": 125, "as": 281, "!": 546, "Number": 435, "to": 107, "global": 541, "max": 211, "match": 278, "state": 102, "val": 63, "appendTo": 897, "extends": 830, "id": 141, "sum": 824, "edge": 818, "stream": 137, "some": 864, "blue": 658, "space": 984, "clamp": 531, "must": 928, "concat": 629, "stat": 940, "can": 325, "lineStart": 837, "background": 474, "inDelta": 148, "famous": 708, "200": 372, "area": 400, "mean": 584, "display": 399, "defaults": 579, "x1": 593, "populatePanel": 365, "current": 713, "e": 122, "c": 105, "width:": 725, "|": 282, "module": 307, "starting": 529, "disabled": 592, "deepEqual": 43, "4;": 756, "timeFormat": 744, "Buffer": 632, "count": 236, "series": 318, "throw": 317, "position": 284, "range": 79, "replset": 773, "y2": 866, "scaleLinear": 653, "x0": 886, "prefix": 734, "promise": 999, "root": 168, "an": 222, "2009": 255, "method": 449, "timeSunday": 809, "01": 106, "spec": 411, "removes": 718, "gd": 990, "voronoi": 808, "domain:": 931, "selected": 486, "two": 346, "coordinates:": 525, "coerces": 608, "floor": 269, "60": 600, "fill": 283, "be": 87, "forEach": 313, "_chart": 74, "select": 84, "<<": 445, "http": 585, "1e": 171, ":": 30, "daylight": 946, "d3": 39, "eat": 859, ">": 180, "replace": 361, "45": 604, "in": 146, "xScale": 679, "y0": 964, "length;": 268, "path": 103, "appendChild": 595, "sslCA": 995, "delete": 530, "finalObj": 729, "2;": 526, "2008": 273, "list": 656, "__data__": 802, "click": 287, "while": 493, "virtual": 528, "id=": 747, "component": 796, "port": 438, "08": 630, "views": 919, "ll": 580, "filters": 849, "shape": 398, "green": 879, "dialog": 506, "code": 617, "exports": 130, "content": 479, "21": 954, "visible": 675, "query": 425, "53": 874, "default": 185, "http:": 724, "2007": 396, "ur": 568, "09": 547, "pattern": 639, "item": 271, "throws": 516, "len": 703, "03": 664, "generates": 667, "|\\": 927, "object": 205, "scalePow": 692, "startDate": 782, "interpolate": 309, "returns": 80, "=": 11, "tree": 960, "prototype": 119, "matrix": 730, "LocusZoom": 988, "75": 994, "ch": 371, "2": 27, "ui": 349, "evt": 509, "o": 225, "error": 196, "number": 203, "999": 535, "columns": 968, "scaleObserver": 408, "status": 475, "prev": 661, "loader": 746, "co": 660, "endDate": 826, "servers": 702, "from": 191, "no": 430, "tags": 962, "panels": 610, "location": 414, "constructor": 464, "socketOptions": 362, "load": 793, "trace": 739, "boolean": 442, "c:": 697, "plan": 221, "view": 500, "cursor": 670, "route": 502, "jsdom": 296, "stats": 821, "arrays": 199, "obj": 187, "&": 487, "String": 732, "ctx": 190, "]": 15, "linear": 389, "left:": 745, "values": 198, "foo": 69, "data;": 742, "now": 392, "&&": 73, "isUndefined": 871, "filename": 887, "copy": 465, "52": 678, "fn": 369, "15": 248, "find": 312, "round": 403, "2010": 145, "same": 341, "1:": 992, "0;": 138, "aSourceMap": 983, "let": 132, "$element": 503, "for": 136, "res": 189, "level": 712, "CodeMirror": 738, "column": 646, "fs": 183, "geometry": 987, "precision": 905, "const": 81, "should": 54, "idx": 997, "comment": 888, "right": 207, "link": 453, "instance": 967, "hover": 843, "/": 23, "parseInt": 816, "handles": 939, "azimuthal": 771, "1990": 327, "opt": 751, "line": 177, "widget": 912, "pop": 806, "x:": 388, "d;": 929, "0xff": 488, "point": 275, "exit": 461, "asdf": 963, "height:": 790, "name:": 735, "force": 789, "<": 157, "Reveal": 774, "inner": 817, "arguments": 339, "lineTo": 355, "io": 819, "$": 109, "dy": 571, "call": 97, "coords": 436, "start": 172, "data": 40, "cwd": 548, "lineChart": 680, "dragging": 991, "createElement": 704, "generate": 652, "actual": 359, "mapping": 764, "register": 228, "js": 230, "and": 208, "instanceof": 478, "38": 977, "><": 457, "m_this": 913, "clip": 894, "layout": 197, "extend": 483, "aliases": 769, "tag": 760, "isFalse": 867, "once": 911, "active": 447, "2003": 407, "express": 753, "addClass": 582, "info": 220, "c1": 861, "empty": 270, "headers": 716, "source": 301, "g": 115, "original": 783, "v": 311, "api": 918, "set": 96, "close": 379, "opacity": 345, "barChart": 462, "parseFloat": 965, "tick": 932, "block": 553, "dest": 914, "value:": 545, "===": 77, "14": 428, "transform": 242, "else": 90, "underTest": 569, "tween": 668, "shift": 883, "json": 315, "opts": 195, "keys": 319, "second": 619, "<=": 762, "ex": 893, "plot": 201, "_options": 591, "emit": 455, "strictEqual": 214, "25": 463, "_this": 915, "cx": 561, "13": 212, "defined": 942, "the": 53, "command": 910, "trigger": 409, "inp": 677, "void": 925, "w": 350, "<SOS>": 2, "geo": 822, "27": 543, "selectAll": 163, "reason": 981, "Error": 272, "ease": 328, "before": 936, "have": 321, "\"": 9, "index": 133, "that": 216, "iD": 733, "allSettings": 644, "components": 855, "try": 650, "graph": 380, "parsed": 961, "packet": 844, "A": 416, "hidden": 671, "slot": 835, "ul": 519, "viz": 347, "datepicker": 424, "are": 534, "projection": 780, "NaN": 358, "years": 836, "result": 244, "90": 533, "100;": 815, "table": 427, "width;": 846, "request": 406, "counter": 748, "x;": 701, "points": 440, "helper": 554, "get:": 472, "lines": 524, "el": 251, "05": 737, "days": 973, "tape": 51, "field": 574, "React": 401, "div": 83, "==": 98, "minute": 838, "h": 364, "read": 669, "moveTo": 641, "pow": 397, "Array": 522, "PI": 758, "[": 14, "dimensions": 920, "at": 460, "listener": 557, "strings": 922, "parentNode": 508, "doc": 517, "errors": 788, "className": 234, "attrs": 850, "circle": 496, "wsint64": 842, "metadata": 757, "a:": 480, "07": 798, "props": 139, "year": 277, "=>": 181, "app": 654, "Polygon": 767, "alpha": 985, "valType:": 944, "beforeEach": 980, "oneOfType": 847, "sources": 684, "tt": 848, "anchor": 786, "svg": 117, "baz": 559, "dc": 657, "tooltips": 870, "clone": 825, "40": 777, "open": 567, "use": 217, "it": 112, "little": 439, "isNaN": 413, "process": 292, "next": 286, "transition": 194, "f": 167, "main": 404, ")": 6, "integer": 834, "glob": 770, "rect": 405, "eatWhile": 792, "polygon": 357, "which": 467, "attributes": 395, "properties": 422, "dim": 953, "toString": 426, "subject": 602, "support": 906, "y:": 387, "params": 118, "csv": 880, "jasmine": 446, "each": 360, "2000": 930, "smd": 491, "events": 499, "$0": 495, "NativeMethodsMixin": 881, "every": 624, "r": 218, "scaleUtc": 616, "create": 473, "utcWeek": 996, "timeWeek": 993, "setTimeout": 594, "7": 75, "cell": 659, "bounds": 540, "then": 749, "describe": 450, "cur": 986, "color": 159, "this": 16, "z": 444, "func": 674, "row": 342, "scope": 261, "random": 575, "dsv": 441, "d3_selection": 797, "util": 249, "ld": 555, "hasOwnProperty": 784, "optimist": 726, "CSSOM": 332, "has": 256, "02": 227, "'": 10, "a": 44, "offset": 173, "add": 188, "assert": 26, "false;": 179, ".": 4, "100%": 959, "stack": 507, "guide": 471, "p": 149, "push": 127, "x2": 979, "db": 363, "previous": 885, "async": 662, "StyleSheet": 645, "missing": 958, "128": 587, "box": 323, "bisectLeft": 839, "url": 306, "JSON": 637, "passed": 443, "generator": 971, "2011": 48, "slice": 421, "render": 265, "event": 155, "!=": 204, "}": 13, "argv": 338, "chart": 95, "delay": 469, "store": 904, "zoom": 288, "gulp": 344, "11": 111, "translate": 298, "bottom": 258, "_bitField": 366, "proxy": 945, "base": 523, "y": 67, "by": 596, "*": 59, "exec": 620, "export": 665, "%d": 969, "false": 100, "timeMonth": 489, "typeof": 128, "12": 129, "history": 621, "0x00000000": 937, "00": 93, "0x00": 245, "int": 468, "666667": 795, "allows": 934, "indexOf": 481, "switch": 723, "left": 147, "apply": 376, "\\": 193, "canvas": 588, "id:": 589, "(": 5, "time": 89, "binary_reply": 368, "closePath": 865, "Jan": 170, "class=": 454, "1;": 293, "null": 52, "first": 485, "utcSunday": 811, "#": 564, "utc": 57, "month": 510, "alias": 714, "dp": 907, "4": 45, "04": 459, "p1": 812, "zero": 736, "import": 303, "type": 99, "is": 116, "locale": 699, "core": 691, "search": 900, "settings": 290, "sets": 785, "resolve": 420, "`": 673, ",": 7, "180": 649, "or": 565, "req": 295, "big": 391, "test": 18, "right;": 884, "ret": 324, "28": 456, "duration": 253, "grid": 558, "arg": 550, "exponent": 437, "5": 41, "socket": 612, "center": 706, "console": 219, "toBe": 274, "internal": 563, "features": 611, "NativeModules": 974, "isTrue": 498, "ok": 153, "when": 412, "jQuery": 402, "master": 720, "self": 47, "host": 514, "beginPath": 794, "i": 46, "p0": 840, "datum": 381, "tooltip": 267, "stop": 304, "file": 418, "getElementsByTagName": 765, "rgb": 505, "config": 152, "text": 134, "M0": 721, "120": 707, "s": 65, "none": 643, "preventDefault": 518, "europe": 556, "hour": 743, "100": 202, "date": 34, "9": 72, "top": 158, "sc": 655, "collection": 370, "value": 55, "1": 21, "isNull": 948, "legend": 410, "psv": 998, "Math": 131, "?": 60, "utcMonth": 663, "parser": 536, "k": 538, "$scope": 763, "B": 740, "interval": 841, "container": 233, "1991": 490, "expected": 210, "20": 174, "b": 76, "map": 92, "entries": 710, "changed": 869, "update": 340, "inherit": 955, "Component": 810, "!this": 417, "specified": 354, "slider": 640, "j": 515, "array": 151, "t": 38, "specs": 731, "!==": 150, "wdouble": 933, "coffee": 970, "append": 91, "domain": 82, "direction": 805, "l": 310, "strict": 213, "xAxis": 951, "callCount": 868, "true;": 192, "bottom:": 876, "grunt": 896, "connection": 715, "err": 209, "dx": 863, "this;": 285, "<UNK>": 1, "parent": 250, "querySelector": 532, "enter": 305, "Promise": 320, "06": 382, "bind": 176}